usetools/__init__.py
usetools/addfunction.py
usetools-0.0.3.dist-info/LICENSE.txt
usetools-0.0.3.dist-info/METADATA
usetools-0.0.3.dist-info/WHEEL
usetools-0.0.3.dist-info/top_level.txt
usetools-0.0.3.dist-info/RECORD
