Metadata-Version: 2.1
Name: usetools
Version: 0.0.3
Summary: Additional functions for python scripts
Author-email: Lucas Borges <lucas.borges@fysik.su.se>
Project-URL: Homepage, https://gitlab.fysik.su.se/lucas.borges/addfunctions
Classifier: Programming Language :: Python :: 3
Classifier: License :: OSI Approved :: MIT License
Classifier: Operating System :: OS Independent
Requires-Python: >=3.6
License-File: LICENSE.txt
